My_Gui_lib/Core.py
My_Gui_lib/__int__.py
My_Gui_lib/widgets.py
my_modern_gui-0.1.0.dist-info/licenses/LICENSE
my_modern_gui-0.1.0.dist-info/METADATA
my_modern_gui-0.1.0.dist-info/WHEEL
my_modern_gui-0.1.0.dist-info/top_level.txt
my_modern_gui-0.1.0.dist-info/RECORD
