Metadata-Version: 2.4
Name: my_modern_gui
Version: 0.1.0
Summary: A professional wrapper for CustomTkinter
Author-email: Your Name <your@email.com>
Project-URL: Homepage, https://github.com/yourusername/yourrepo
Classifier: Programming Language :: Python :: 3
Classifier: License :: OSI Approved :: MIT License
Classifier: Operating System :: OS Independent
Requires-Python: >=3.7
License-File: LICENSE
Requires-Dist: customtkinter
Dynamic: license-file
